risc_processor.v
// RISC Processor Module: A simple 8-bit RISC processor with basic instructions
// This processor supports a small set of instructions: ADD, SUB, LOAD, STORE, and JUMP.
// It includes a program counter, instruction memory, data memory, ALU, and control unit.


module risc_processor (
    input clk,                    // Clock signal
    input reset,                  // Reset signal (active high)
    input [7:0] external_data_in, // External data input
    output [7:0] data_out         // Data output 
);

    // Internal wires and registers

    // Program counter: current address, next address, and address + 1
    wire [7:0] pc_current;  // Current instruction address
    wire [7:0] pc_next;     // Next instruction address
    wire [7:0] pc_plus1;    // Current address + 1 (for sequential execution)


    // Instruction fetched from memory
    wire [15:0] instruction;


    // Instruction fields
    wire [2:0] opcode;      // 3-bit opcode (ADD, SUB, LOAD, STORE, JUMP)
    wire [1:0] rd;          // Destination/target register (2 bits, 4 registers)
    wire [1:0] rs1;         // Source register 1
    wire [1:0] rs2;         // Source register 2
    wire [7:0] immediate;   // Immediate value or offset

    // Control signals
    wire reg_write;         // Enable register writeback
    wire mem_read;          // Enable memory read
    wire mem_write;         // Enable memory write
    wire alu_src;           // Select ALU input (register or immediate)
    wire alu_op;            // ALU operation (ADD or SUB)
    wire pc_src;            // Select next PC (PC+1 or jump target)

    // Data wires
    wire [7:0] read_data1;  // Data read from register 1
    wire [7:0] read_data2;  // Data read from register 2
    wire [7:0] alu_b;       // ALU input B (from register or immediate)
    wire [7:0] alu_result;  // ALU output
    wire [7:0] mem_read_data; // Data read from memory (including I/O)
    wire [7:0] write_data_reg; // Data to write to register

    // Program Counter module: tracks current instruction address
    pc pc_inst (
        .clk(clk),          // Clock input
        .reset(reset),      // Reset input
        .next_pc(pc_next),  // Next address to jump to
        .current_pc(pc_current) // Current address output
    );

    // Calculate next sequential address
    assign pc_plus1 = pc_current + 1;

    // Determine next PC: jump target (from instruction) or PC+1
    assign pc_next = (pc_src) ? {1'b0, instruction[6:0]} : pc_plus1;

    // Instruction Memory (ROM): stores program instructions
    instruction_memory imem (
        .address(pc_current),   // Address to read from
        .instruction(instruction) // Instruction output
    );

    // Instruction parsing: extract fields from instruction
    assign opcode = instruction[15:13]; // Opcode: bits 15-13
    assign rd = instruction[12:11];     // Destination register: bits 12-11
    assign rs1 = instruction[10:9];     // Source register 1: bits 10-9
    assign rs2 = instruction[8:7];      // Source register 2: bits 8-7
    assign immediate = instruction[7:0]; // Immediate/offset: bits 7-0

    // Control Unit: decodes opcode and generates control signals
    control_unit ctrl (
        .opcode(opcode),      // Opcode input
        .reg_write(reg_write), // Register write enable
        .mem_read(mem_read),   // Memory read enable
        .mem_write(mem_write), // Memory write enable
        .alu_src(alu_src),     // ALU input select
        .alu_op(alu_op),       // ALU operation select
        .pc_src(pc_src)        // PC source select
    );

    // Register File: stores 4 general-purpose 8-bit registers
    register_file rf (
        .reset(reset),         // Reset signal
        .clk(clk),             // Clock input
        .reg_write(reg_write), // Write enable
        .read_reg1(rs1),       // Read register 1 address
        .read_reg2(rs2),       // Read register 2 address
        .write_reg(rd),        // Write register address
        .write_data(write_data_reg), // Data to write
        .read_data1(read_data1),     // Data from register 1
        .read_data2(read_data2)      // Data from register 2
    );

    // ALU input multiplexer: selects between register and immediate
    assign alu_b = (alu_src) ? immediate : read_data2;

    // ALU: performs ADD or SUB
    alu alu_inst (
        .a(read_data1),        // Input A (from register)
        .b(alu_b),             // Input B (from mux)
        .op(alu_op),           // Operation (ADD or SUB)
        .result(alu_result)    // ALU result
    );

    // Data Memory (RAM with I/O): stores data and handles I/O
    data_memory dmem (
        .clk(clk),             // Clock input
        .mem_read(mem_read),   // Read enable
        .mem_write(mem_write), // Write enable
        .address(alu_result),  // Address to read/write
        .write_data(read_data2), // Data to write
        .read_data(mem_read_data), // Data read from memory/I/O
        .external_data_in(external_data_in) // External data input
    );

    // Writeback multiplexer: selects between ALU result and memory data
    assign write_data_reg = (opcode == 3'b010) ? mem_read_data : alu_result;

    // Optional: data output for external devices (e.g., store to output port)
    // If writing to address 0xFF, output the data
    assign data_out = (mem_write && alu_result == 8'hFF) ? read_data2 : 8'h00;

endmodule






// Program Counter module: tracks current instruction address
module pc (
    input clk,
    input reset,
    input [7:0] next_pc,
    output reg [7:0] current_pc
);
    always @(posedge clk or posedge reset) begin
        if (reset) current_pc <= 0;
        else current_pc <= next_pc;
    end
endmodule






// Instruction Memory (ROM): stores program instructions
module instruction_memory (
    input [7:0] address,
    output [15:0] instruction
);
    reg [15:0] rom [0:255];
    integer i;
    initial begin
        // CORRECTED INSTRUCTIONS:
        rom[0] = 16'h4810; // LOAD R1, 0x10(R0)   [010_01_00_00_00010000]
        rom[1] = 16'h1200; // ADD R2, R1, R0      [000_10_01_00_00000000]
        rom[2] = 16'h7020; // STORE R2, 0x20(R0)  [011_10_00_00_00100000]
        rom[3] = 16'h8005; // JUMP 0x05           [100_00_00_00_00000101]
        for (i=4; i<256; i=i+1) rom[i] = 16'h0000;
    end
    assign instruction = rom[address];
endmodule






// Control Unit: decodes opcode and generates control signals
module control_unit (
    input [2:0] opcode,
    output reg reg_write,
    output reg mem_read,
    output reg mem_write,
    output reg alu_src,
    output reg alu_op,
    output reg pc_src
);
    always @(*) begin
        // DEFAULT ALL SIGNALS TO 0
        {reg_write, mem_read, mem_write, alu_src, alu_op, pc_src} = 0;
        
        case (opcode)
            3'b000: begin // ADD
                reg_write = 1;
                alu_op   = 0;
            end
            3'b001: begin // SUB
                reg_write = 1;
                alu_op   = 1;
            end
            3'b010: begin // LOAD
                reg_write = 1;
                mem_read  = 1;
                alu_src   = 1;  // Use immediate
                alu_op    = 0;  // ADD for address calc
            end
            3'b011: begin // STORE
                mem_write = 1;
                alu_src   = 1;  // Use immediate
                alu_op    = 0;  // ADD for address calc
            end
            3'b100: begin // JUMP
                pc_src = 1;
            end
            default: begin // Default case
                reg_write = 0;
                mem_read  = 0;
                mem_write = 0;
                alu_src   = 0;
                alu_op    = 0;
                pc_src    = 0;
            end
        endcase
    end
endmodule






// Register File: stores 4 general-purpose 8-bit registers
module register_file (
    input reset,
    input clk,                // Clock signal
    input reg_write,          // Write enable
    input [1:0] read_reg1,    // Read register 1 address
    input [1:0] read_reg2,    // Read register 2 address
    input [1:0] write_reg,    // Write register address
    input [7:0] write_data,   // Data to write
    output reg [7:0] read_data1, // Data from register 1
    output reg [7:0] read_data2  // Data from register 2
);
    reg [7:0] regs [0:3];     // 4x8-bit registers

    initial begin // Initialize registers to 0
        // Set all registers to 0 at startup
    regs[0] = 0; regs[1] = 0; regs[2] = 0; regs[3] = 0;
    end


    // Write to register on clock edge if write is enabled
    always @(posedge clk or posedge reset) begin
        if (reset) begin
        regs[0] <= 0; regs[1] <= 0; regs[2] <= 0; regs[3] <= 0;
        end else if (reg_write) begin
        regs[write_reg] <= write_data;
        end
    end


    // Read from registers (combinational)
    always @(*) begin
        read_data1 = regs[read_reg1];
        read_data2 = regs[read_reg2];
    end
endmodule





// ALU: performs ADD or SUB
module alu (
    input [7:0] a,           // Input A
    input [7:0] b,           // Input B
    input op,                // Operation (0: ADD, 1: SUB)
    output reg [7:0] result  // Result output
);
    always @(*) begin
        case (op)
            0: result = a + b; // ADD operation
            1: result = a - b; // SUB operation
            default: result = 8'h00; // Default to 0
        endcase
    end
endmodule





// Data Memory (RAM with I/O): stores data and handles I/O
module data_memory (
    input clk,                // Clock signal
    input mem_read,           // Read enable
    input mem_write,          // Write enable
    input [7:0] address,      // Address to read/write
    input [7:0] write_data,   // Data to write
    output reg [7:0] read_data, // Data read from memory/I/O
    input [7:0] external_data_in // External data input
);
    reg [7:0] ram [0:255];    // 256x8 RAM for data

    // Write to RAM on clock edge if write is enabled and not I/O address
    always @(posedge clk) begin
        if (mem_write && address != 8'hFF)
            ram[address] <= write_data;
    end

    // Read from RAM or external input (combinational)
    always @(*) begin
        if (mem_read) begin
            if (address == 8'hFF) // If address is I/O, read external input
                read_data = external_data_in;
            else                  // Otherwise, read from RAM
                read_data = ram[address];
        end else
            read_data = 8'h00;    // Default output if not reading
    end
endmodule

risc_processor_tb.v
`include "risc_processor.v"
`timescale 1ns / 1ps

module tb_risc_processor();
    reg clk;
    reg reset;
    reg [7:0] external_data_in;
    wire [7:0] data_out;

    // Instantiate the processor
    risc_processor uut (
        .clk(clk),
        .reset(reset),
        .external_data_in(external_data_in),
        .data_out(data_out)
    );

    // Clock generation (100 MHz)
    always #5 clk = ~clk;

    // Hierarchical monitoring
    wire [7:0]  pc_current       = uut.pc_current;
    wire [15:0] instruction      = uut.instruction;
    wire [2:0]  opcode           = uut.opcode;
    wire [7:0]  regs_0           = uut.rf.regs[0];
    wire [7:0]  regs_1           = uut.rf.regs[1];
    wire [7:0]  regs_2           = uut.rf.regs[2];
    wire [7:0]  regs_3           = uut.rf.regs[3];
    wire        pc_src           = uut.pc_src;

    // VCD dump for GTKWave
    initial begin
        $dumpfile("risc_processor_tb.vcd");
        $dumpvars(0, tb_risc_processor);
    end

    // Test sequence
    initial begin
        // Initialize signals
        clk = 0;
        reset = 1;
        external_data_in = 0;

        // Preload data memory
        uut.dmem.ram[8'h10] = 8'hA5;
        uut.dmem.ram[8'h20] = 8'h00;

        // Reset sequence
        #10 reset = 0;
        #10 reset = 1;
        #20 reset = 0;

        $display("--- [TEST 1: RESET] ---");
        $display("PC after reset: %h (expected: 00)", pc_current);
        $display("Registers after reset: R0=%h, R1=%h, R2=%h, R3=%h", 
                 regs_0, regs_1, regs_2, regs_3);
        #10;

        // Test 2: LOAD instruction
        $display("\n--- [TEST 2: LOAD] ---");
        #20;
        $display("After LOAD: R1 = %h (expected: A5)", regs_1);
        if (regs_1 !== 8'hA5) $error("LOAD test failed!");

        // Test 3: ADD instruction
        $display("\n--- [TEST 3: ADD] ---");
        #20;
        $display("After ADD: R2 = %h (expected: A5)", regs_2);
        if (regs_2 !== 8'hA5) $error("ADD test failed!");

        // Test 4: STORE instruction (FIXED)
        $display("\n--- [TEST 4: STORE] ---");
        #20;
        @(posedge clk); // WAIT FOR CLOCK EDGE
        #5;  // Small delay after clock edge
        $display("Data at 0x20: %h (expected: A5)", uut.dmem.ram[8'h20]);
        if (uut.dmem.ram[8'h20] !== 8'hA5) $error("STORE test failed!");

        // Test 5: JUMP instruction (FIXED)
        $display("\n--- [TEST 5: JUMP] ---");
        #20;
        $display("PC after JUMP: %h (expected: 05)", pc_current);
        $display("pc_src = %b, instruction = %h", pc_src, instruction);
        if (pc_current !== 8'h05) $error("JUMP test failed!");

        // Test 6: I/O Read (FIXED)
        $display("\n--- [TEST 6: I/O READ] ---");
        external_data_in = 8'hF0;
        uut.imem.rom[5] = 16'h48FF; // LOAD R1, 0xFF(R0) [010_01_00_00_11111111]
        #20;
        $display("R1 after I/O read: %h (expected: F0)", regs_1);
        if (regs_1 !== 8'hF0) $error("I/O read test failed!");

        // Test 7: SUB instruction (FIXED)
        $display("\n--- [TEST 7: SUB] ---");
        uut.imem.rom[6] = 16'h1D80; // SUB R3, R1, R2 [001_11_01_10_00000000]
        #20;
        $display("After SUB: R3 = %h (expected: 4B)", regs_3);
        if (regs_3 !== 8'h4B) $error("SUB test failed!");

        // Test 8: Reset recovery
        $display("\n--- [TEST 8: RESET RECOVERY] ---");
        #10 reset = 1;
        #20 reset = 0;
        $display("PC after reset: %h (expected: 00)", pc_current);
        if (pc_current !== 8'h00) $error("Reset recovery failed!");

        $display("\nAll tests completed!");
        $finish;
    end

    // Real-time monitoring
    always @(posedge clk) begin
        $display("[%t] CLK: PC=%h, OPCODE=%b, R1=%h, R2=%h", 
                 $time, pc_current, opcode, regs_1, regs_2);
    end
endmodule

risc_processor_tb.vcd
$date
	Sun Jun 29 20:26:53 2025
$end
$version
	Icarus Verilog
$end
$timescale
	1ps
$end
$scope module tb_risc_processor $end
$var wire 16 ! instruction [15:0] $end
$var wire 3 " opcode [2:0] $end
$var wire 8 # pc_current [7:0] $end
$var wire 1 $ pc_src $end
$var wire 8 % regs_0 [7:0] $end
$var wire 8 & regs_1 [7:0] $end
$var wire 8 ' regs_2 [7:0] $end
$var wire 8 ( regs_3 [7:0] $end
$var wire 8 ) data_out [7:0] $end
$var reg 1 * clk $end
$var reg 8 + external_data_in [7:0] $end
$var reg 1 , reset $end
$scope module uut $end
$var wire 1 * clk $end
$var wire 8 - external_data_in [7:0] $end
$var wire 1 , reset $end
$var wire 8 . write_data_reg [7:0] $end
$var wire 2 / rs2 [1:0] $end
$var wire 2 0 rs1 [1:0] $end
$var wire 1 1 reg_write $end
$var wire 8 2 read_data2 [7:0] $end
$var wire 8 3 read_data1 [7:0] $end
$var wire 2 4 rd [1:0] $end
$var wire 1 5 pc_src $end
$var wire 8 6 pc_plus1 [7:0] $end
$var wire 8 7 pc_next [7:0] $end
$var wire 8 8 pc_current [7:0] $end
$var wire 3 9 opcode [2:0] $end
$var wire 1 : mem_write $end
$var wire 8 ; mem_read_data [7:0] $end
$var wire 1 < mem_read $end
$var wire 16 = instruction [15:0] $end
$var wire 8 > immediate [7:0] $end
$var wire 8 ? data_out [7:0] $end
$var wire 1 @ alu_src $end
$var wire 8 A alu_result [7:0] $end
$var wire 1 B alu_op $end
$var wire 8 C alu_b [7:0] $end
$scope module alu_inst $end
$var wire 8 D b [7:0] $end
$var wire 1 B op $end
$var wire 8 E a [7:0] $end
$var reg 8 F result [7:0] $end
$upscope $end
$scope module ctrl $end
$var wire 3 G opcode [2:0] $end
$var reg 1 B alu_op $end
$var reg 1 @ alu_src $end
$var reg 1 < mem_read $end
$var reg 1 : mem_write $end
$var reg 1 5 pc_src $end
$var reg 1 1 reg_write $end
$upscope $end
$scope module dmem $end
$var wire 8 H address [7:0] $end
$var wire 1 * clk $end
$var wire 8 I external_data_in [7:0] $end
$var wire 1 < mem_read $end
$var wire 1 : mem_write $end
$var wire 8 J write_data [7:0] $end
$var reg 8 K read_data [7:0] $end
$upscope $end
$scope module imem $end
$var wire 16 L instruction [15:0] $end
$var wire 8 M address [7:0] $end
$var integer 32 N i [31:0] $end
$upscope $end
$scope module pc_inst $end
$var wire 1 * clk $end
$var wire 8 O next_pc [7:0] $end
$var wire 1 , reset $end
$var reg 8 P current_pc [7:0] $end
$upscope $end
$scope module rf $end
$var wire 1 * clk $end
$var wire 2 Q read_reg1 [1:0] $end
$var wire 2 R read_reg2 [1:0] $end
$var wire 1 1 reg_write $end
$var wire 1 , reset $end
$var wire 8 S write_data [7:0] $end
$var wire 2 T write_reg [1:0] $end
$var reg 8 U read_data1 [7:0] $end
$var reg 8 V read_data2 [7:0] $end
$upscope $end
$upscope $end
$upscope $end
$enddefinitions $end
#0
$dumpvars
b0 V
b0 U
b1 T
b10100101 S
b0 R
b0 Q
b0 P
b1 O
b100000000 N
b0 M
b100100000010000 L
b10100101 K
b0 J
b0 I
b10000 H
b10 G
b10000 F
b0 E
b10000 D
b10000 C
0B
b10000 A
1@
b0 ?
b10000 >
b100100000010000 =
1<
b10100101 ;
0:
b10 9
b0 8
b1 7
b1 6
05
b1 4
b0 3
b0 2
11
b0 0
b0 /
b10100101 .
b0 -
1,
b0 +
0*
b0 )
b0 (
b0 '
b0 &
b0 %
0$
b0 #
b10 "
b100100000010000 !
$end
#5000
1*
#10000
0*
0,
#15000
b10100101 A
b10100101 F
b10100101 H
b0 ;
b0 K
b0 C
b0 D
b10100101 3
b10100101 E
b10100101 U
b10100101 .
b10100101 S
11
0<
0@
b0 >
b1 0
b1 Q
b10 4
b10 T
b0 "
b0 9
b0 G
b10 7
b10 O
b1001000000000 !
b1001000000000 =
b1001000000000 L
b10 6
b1 #
b1 8
b1 M
b1 P
b10100101 &
1*
#20000
b10000 C
b10000 D
b10100101 ;
b10100101 K
b10000 A
b10000 F
b10000 H
b10100101 .
b10100101 S
1@
1<
11
b0 3
b0 E
b0 U
b10000 >
b0 0
b0 Q
b1 4
b1 T
b10 "
b10 9
b10 G
b1 7
b1 O
b0 &
b100100000010000 !
b100100000010000 =
b100100000010000 L
b1 6
b0 #
b0 8
b0 M
b0 P
0*
1,
#25000
1*
#30000
0*
#35000
1*
#40000
0*
0,
#45000
b10100101 A
b10100101 F
b10100101 H
b0 ;
b0 K
b0 C
b0 D
b10100101 3
b10100101 E
b10100101 U
b10100101 .
b10100101 S
11
0<
0@
b0 >
b1 0
b1 Q
b10 4
b10 T
b0 "
b0 9
b0 G
b10 7
b10 O
b1001000000000 !
b1001000000000 =
b1001000000000 L
b10 6
b1 #
b1 8
b1 M
b1 P
b10100101 &
1*
#50000
0*
#55000
b100000 .
b100000 S
b100000 C
b100000 D
b100000 A
b100000 F
b100000 H
1@
1:
01
b0 3
b0 E
b0 U
b100000 >
b0 0
b0 Q
b11 "
b11 9
b11 G
b11 7
b11 O
b10100101 '
b111000000100000 !
b111000000100000 =
b111000000100000 L
b11 6
b10 #
b10 8
b10 M
b10 P
1*
#60000
0*
#65000
b0 .
b0 S
b0 A
b0 F
b0 H
b0 C
b0 D
1$
15
0:
0@
b101 >
b0 4
b0 T
b100 "
b100 9
b100 G
b101 7
b101 O
b1000000000000101 !
b1000000000000101 =
b1000000000000101 L
b100 6
b11 #
b11 8
b11 M
b11 P
1*
#70000
0*
#75000
11
0$
05
b110 7
b110 O
b0 >
b0 "
b0 9
b0 G
b0 !
b0 =
b0 L
b110 6
b101 #
b101 8
b101 M
b101 P
1*
#80000
0*
#85000
b111 7
b111 O
b111 6
b110 #
b110 8
b110 M
b110 P
1*
#90000
0*
#95000
b1000 7
b1000 O
b1000 6
b111 #
b111 8
b111 M
b111 P
1*
#100000
0*
#105000
b1001 7
b1001 O
b1001 6
b1000 #
b1000 8
b1000 M
b1000 P
1*
#110000
0*
#115000
b1010 7
b1010 O
b1010 6
b1001 #
b1001 8
b1001 M
b1001 P
1*
#120000
0*
#125000
b1011 7
b1011 O
b1011 6
b1010 #
b1010 8
b1010 M
b1010 P
1*
#130000
0*
#135000
b1100 7
b1100 O
b1100 6
b1011 #
b1011 8
b1011 M
b1011 P
1*
#140000
0*
b11110000 +
b11110000 -
b11110000 I
#145000
b1101 7
b1101 O
b1101 6
b1100 #
b1100 8
b1100 M
b1100 P
1*
#150000
0*
#155000
b1110 7
b1110 O
b1110 6
b1101 #
b1101 8
b1101 M
b1101 P
1*
#160000
0*
#165000
b1111 7
b1111 O
b1111 6
b1110 #
b1110 8
b1110 M
b1110 P
1*
#170000
0*
#175000
b10000 7
b10000 O
b10000 6
b1111 #
b1111 8
b1111 M
b1111 P
1*
#180000
0*
#185000
b10001 7
b10001 O
b10001 6
b10000 #
b10000 8
b10000 M
b10000 P
1*
#190000
b10000 A
b10000 F
b10000 H
b10100101 .
b10100101 S
b10000 C
b10000 D
b10100101 ;
b10100101 K
1@
1<
11
b10000 >
b1 4
b1 T
b10 "
b10 9
b10 G
b1 7
b1 O
b0 '
b0 &
b100100000010000 !
b100100000010000 =
b100100000010000 L
b1 6
b0 #
b0 8
b0 M
b0 P
0*
1,
#195000
1*
#200000
0*
#205000
1*
#210000
0*
0,
